pygeoboundaries/__init__.py
pygeoboundaries/pygeoboundaries.py
pygeoboundaries/requirements.txt
pygeoboundaries-0.0.3.dist-info/METADATA
pygeoboundaries-0.0.3.dist-info/WHEEL
pygeoboundaries-0.0.3.dist-info/RECORD
