Metadata-Version: 2.1
Name: pygeoboundaries
Version: 0.0.3
Summary: For performing data checks and file validation on geoboundary files. The primary purpose of this package is to facilitate the review process for pull requests made to the geoBoundaries repository.
Home-page: https://github.com/wmgeolab/pyGeoBoundaries
License: MIT
Keywords: pygeoboundaries,geoboundaries,wmgeolab,metaCheck
Author: rohith4444
Author-email: rohithreddy24242@gmail.com
Requires-Python: >=3.9,<4.0
Classifier: License :: OSI Approved :: MIT License
Classifier: Programming Language :: Python :: 3
Classifier: Programming Language :: Python :: 3.9
Classifier: Programming Language :: Python :: 3.10
Classifier: Programming Language :: Python :: 3.11
Project-URL: Repository, https://github.com/wmgeolab/pyGeoBoundaries
